source_netsuite/__init__.py
source_netsuite/constraints.py
source_netsuite/errors.py
source_netsuite/run.py
source_netsuite/source.py
source_netsuite/spec.yaml
source_netsuite/streams.py
airbyte_source_netsuite-0.1.27.dist-info/METADATA
airbyte_source_netsuite-0.1.27.dist-info/WHEEL
airbyte_source_netsuite-0.1.27.dist-info/entry_points.txt
airbyte_source_netsuite-0.1.27.dist-info/RECORD
