Metadata-Version: 2.1
Name: airbyte-source-netsuite
Version: 0.1.27
Summary: Source implementation for Netsuite.
Home-page: https://airbyte.com
License: ELv2
Author: Airbyte
Author-email: contact@airbyte.io
Requires-Python: >=3.9,<3.12
Classifier: License :: Other/Proprietary License
Classifier: Programming Language :: Python :: 3
Classifier: Programming Language :: Python :: 3.9
Classifier: Programming Language :: Python :: 3.10
Classifier: Programming Language :: Python :: 3.11
Requires-Dist: airbyte-cdk (>=1,<2)
Requires-Dist: requests-oauthlib (>=2.0.0,<3.0.0)
Project-URL: Documentation, https://docs.airbyte.com/integrations/sources/netsuite
Project-URL: Repository, https://github.com/airbytehq/airbyte
